odoo/addons/sale_automatic_workflow_ignore_exception/README.rst
odoo/addons/sale_automatic_workflow_ignore_exception/__init__.py
odoo/addons/sale_automatic_workflow_ignore_exception/__manifest__.py
odoo/addons/sale_automatic_workflow_ignore_exception/i18n/fr.po
odoo/addons/sale_automatic_workflow_ignore_exception/i18n/sale_automatic_workflow_ignore_exception.pot
odoo/addons/sale_automatic_workflow_ignore_exception/models/__init__.py
odoo/addons/sale_automatic_workflow_ignore_exception/models/automatic_workflow_job.py
odoo/addons/sale_automatic_workflow_ignore_exception/models/sale_order.py
odoo/addons/sale_automatic_workflow_ignore_exception/models/sale_workflow_process.py
odoo/addons/sale_automatic_workflow_ignore_exception/readme/CONTRIBUTORS.rst
odoo/addons/sale_automatic_workflow_ignore_exception/readme/DESCRIPTION.rst
odoo/addons/sale_automatic_workflow_ignore_exception/static/description/icon.png
odoo/addons/sale_automatic_workflow_ignore_exception/static/description/index.html
odoo/addons/sale_automatic_workflow_ignore_exception/tests/__init__.py
odoo/addons/sale_automatic_workflow_ignore_exception/tests/test_automatic_workflow_ignore_exception.py
odoo/addons/sale_automatic_workflow_ignore_exception/views/sale_workflow_process.xml
odoo14_addon_sale_automatic_workflow_ignore_exception-14.0.1.0.2.dist-info/METADATA
odoo14_addon_sale_automatic_workflow_ignore_exception-14.0.1.0.2.dist-info/WHEEL
odoo14_addon_sale_automatic_workflow_ignore_exception-14.0.1.0.2.dist-info/top_level.txt
odoo14_addon_sale_automatic_workflow_ignore_exception-14.0.1.0.2.dist-info/RECORD
